AssetAPI-stubs/__init__.pyi
AssetAPI-stubs/py.typed
AssetAPI_cmodule-stubs/__init__.pyi
AssetAPI_cmodule-stubs/py.typed
AssetBrowser-stubs/Browser.pyi
AssetBrowser-stubs/BrowserColumn.pyi
AssetBrowser-stubs/BrowserSettings.pyi
AssetBrowser-stubs/FileBrowser.pyi
AssetBrowser-stubs/FileInfo.pyi
AssetBrowser-stubs/Manifest.pyi
AssetBrowser-stubs/NonexclusiveCheckboxPopup.pyi
AssetBrowser-stubs/__init__.pyi
AssetBrowser-stubs/py.typed
CacheManager-stubs/__init__.pyi
CacheManager-stubs/py.typed
Callbacks-stubs/Callbacks.pyi
Callbacks-stubs/Manifest.pyi
Callbacks-stubs/__init__.pyi
Callbacks-stubs/py.typed
CatalogAPI-stubs/Catalog.pyi
CatalogAPI-stubs/CatalogItem.pyi
CatalogAPI-stubs/CatalogUtils.pyi
CatalogAPI-stubs/Client.pyi
CatalogAPI-stubs/__init__.pyi
CatalogAPI-stubs/py.typed
ConditionalStateGrammar-stubs/Parser.pyi
ConditionalStateGrammar-stubs/__init__.pyi
ConditionalStateGrammar-stubs/py.typed
ConfigurationAPI_cmodule-stubs/__init__.pyi
ConfigurationAPI_cmodule-stubs/py.typed
DrawingModule-stubs/AutoPosition.pyi
DrawingModule-stubs/CustomColors.pyi
DrawingModule-stubs/Manifest.pyi
DrawingModule-stubs/NodeShapeAttrUtil.pyi
DrawingModule-stubs/__init__.pyi
DrawingModule-stubs/py.typed
GeoAPI-stubs/Lookfiles.pyi
GeoAPI-stubs/Manifest.pyi
GeoAPI-stubs/Transform.pyi
GeoAPI-stubs/Util/ArgsFileUtil.pyi
GeoAPI-stubs/Util/CelUtil.pyi
GeoAPI-stubs/Util/GenericAppenderUtil.pyi
GeoAPI-stubs/Util/HintDictUtil.pyi
GeoAPI-stubs/Util/LookFileUtil.pyi
GeoAPI-stubs/Util/Manifest.pyi
GeoAPI-stubs/Util/Matrix.pyi
GeoAPI-stubs/Util/__init__.pyi
GeoAPI-stubs/__init__.pyi
GeoAPI-stubs/py.typed
Katana-stubs/__init__.pyi
Katana-stubs/py.typed
KatanaResources-stubs/Manifest.pyi
KatanaResources-stubs/ResourceFiles.pyi
KatanaResources-stubs/__init__.pyi
KatanaResources-stubs/py.typed
LoggingAPI-stubs/__init__.pyi
LoggingAPI-stubs/py.typed
LookFileBakeAPI-stubs/Constants.pyi
LookFileBakeAPI-stubs/Exceptions.pyi
LookFileBakeAPI-stubs/LookFileBaker.pyi
LookFileBakeAPI-stubs/LookFileUtil.pyi
types_katana-5.0.5.0.dist-info/METADATA
types_katana-5.0.5.0.dist-info/WHEEL
types_katana-5.0.5.0.dist-info/RECORD
